ksr.py
ksr-0.1.5.dist-info/DESCRIPTION.rst
ksr-0.1.5.dist-info/entry_points.txt
ksr-0.1.5.dist-info/METADATA
ksr-0.1.5.dist-info/metadata.json
ksr-0.1.5.dist-info/RECORD
ksr-0.1.5.dist-info/top_level.txt
ksr-0.1.5.dist-info/WHEEL
