Metadata-Version: 2.0
Name: ksr
Version: 0.1.5
Summary: commandline kickstarter
Home-page: https://github.com/jedahan/kickstarter
Author: Jonathan Dahan
Author-email: jonathan@jonathan.is
License: ISC
Download-URL: https://github.com/jedahan/kickstarter/tarball/0.1.3
Keywords: kickstarter
Platform: UNKNOWN
Classifier: Development Status :: 4 - Beta
Classifier: Environment :: Console
Classifier: License :: OSI Approved :: ISC License (ISCL)
Classifier: Natural Language :: English
Classifier: Operating System :: MacOS :: MacOS X
Classifier: Operating System :: POSIX :: Linux
Classifier: Programming Language :: Python :: 3
Classifier: Programming Language :: Python :: 3.5
Classifier: Topic :: Software Development :: User Interfaces
Classifier: Topic :: Utilities
Requires-Dist: Click
Requires-Dist: TinyDB
